{
  "metadata": {
    "toolPackage": "@microsoft/api-extractor",
    "toolVersion": "7.34.4",
    "schemaVersion": 1011,
    "oldestForwardsCompatibleVersion": 1001,
    "tsdocConfig": {
      "$schema": "https://developer.microsoft.com/json-schemas/tsdoc/v0/tsdoc.schema.json",
      "noStandardTags": true,
      "tagDefinitions": [
        {
          "tagName": "@alpha",
          "syntaxKind": "modifier"
        },
        {
          "tagName": "@beta",
          "syntaxKind": "modifier"
        },
        {
          "tagName": "@defaultValue",
          "syntaxKind": "block"
        },
        {
          "tagName": "@decorator",
          "syntaxKind": "block",
          "allowMultiple": true
        },
        {
          "tagName": "@deprecated",
          "syntaxKind": "block"
        },
        {
          "tagName": "@eventProperty",
          "syntaxKind": "modifier"
        },
        {
          "tagName": "@example",
          "syntaxKind": "block",
          "allowMultiple": true
        },
        {
          "tagName": "@experimental",
          "syntaxKind": "modifier"
        },
        {
          "tagName": "@inheritDoc",
          "syntaxKind": "inline"
        },
        {
          "tagName": "@internal",
          "syntaxKind": "modifier"
        },
        {
          "tagName": "@label",
          "syntaxKind": "inline"
        },
        {
          "tagName": "@link",
          "syntaxKind": "inline",
          "allowMultiple": true
        },
        {
          "tagName": "@override",
          "syntaxKind": "modifier"
        },
        {
          "tagName": "@packageDocumentation",
          "syntaxKind": "modifier"
        },
        {
          "tagName": "@param",
          "syntaxKind": "block",
          "allowMultiple": true
        },
        {
          "tagName": "@privateRemarks",
          "syntaxKind": "block"
        },
        {
          "tagName": "@public",
          "syntaxKind": "modifier"
        },
        {
          "tagName": "@readonly",
          "syntaxKind": "modifier"
        },
        {
          "tagName": "@remarks",
          "syntaxKind": "block"
        },
        {
          "tagName": "@returns",
          "syntaxKind": "block"
        },
        {
          "tagName": "@sealed",
          "syntaxKind": "modifier"
        },
        {
          "tagName": "@see",
          "syntaxKind": "block"
        },
        {
          "tagName": "@throws",
          "syntaxKind": "block",
          "allowMultiple": true
        },
        {
          "tagName": "@typeParam",
          "syntaxKind": "block",
          "allowMultiple": true
        },
        {
          "tagName": "@virtual",
          "syntaxKind": "modifier"
        },
        {
          "tagName": "@betaDocumentation",
          "syntaxKind": "modifier"
        },
        {
          "tagName": "@internalRemarks",
          "syntaxKind": "block"
        },
        {
          "tagName": "@preapproved",
          "syntaxKind": "modifier"
        }
      ],
      "supportForTags": {
        "@alpha": true,
        "@beta": true,
        "@defaultValue": true,
        "@decorator": true,
        "@deprecated": true,
        "@eventProperty": true,
        "@example": true,
        "@experimental": true,
        "@inheritDoc": true,
        "@internal": true,
        "@label": true,
        "@link": true,
        "@override": true,
        "@packageDocumentation": true,
        "@param": true,
        "@privateRemarks": true,
        "@public": true,
        "@readonly": true,
        "@remarks": true,
        "@returns": true,
        "@sealed": true,
        "@see": true,
        "@throws": true,
        "@typeParam": true,
        "@virtual": true,
        "@betaDocumentation": true,
        "@internalRemarks": true,
        "@preapproved": true
      },
      "reportUnsupportedHtmlElements": false
    }
  },
  "kind": "Package",
  "canonicalReference": "@webex/internal-plugin-ediscovery!",
  "docComment": "",
  "name": "@webex/internal-plugin-ediscovery",
  "preserveMemberOrder": false,
  "members": [
    {
      "kind": "EntryPoint",
      "canonicalReference": "@webex/internal-plugin-ediscovery!",
      "name": "",
      "preserveMemberOrder": false,
      "members": [
        {
          "kind": "Variable",
          "canonicalReference": "@webex/internal-plugin-ediscovery!EDiscovery:var",
          "docComment": "/**\n * @class EDiscovery is used by compliance officers to run compliance reports\n */\n",
          "excerptTokens": [
            {
              "kind": "Content",
              "text": "EDiscovery: "
            },
            {
              "kind": "Content",
              "text": "any"
            }
          ],
          "fileUrlPath": "dist/types/ediscovery.d.ts",
          "isReadonly": true,
          "releaseTag": "Public",
          "name": "EDiscovery",
          "variableTypeTokenRange": {
            "startIndex": 1,
            "endIndex": 2
          }
        },
        {
          "kind": "Class",
          "canonicalReference": "@webex/internal-plugin-ediscovery!EdiscoveryError:class",
          "docComment": "/**\n * General ediscovery error\n */\n",
          "excerptTokens": [
            {
              "kind": "Content",
              "text": "export class EdiscoveryError "
            }
          ],
          "fileUrlPath": "dist/types/ediscovery-error.d.ts",
          "releaseTag": "Public",
          "isAbstract": false,
          "name": "EdiscoveryError",
          "preserveMemberOrder": false,
          "members": [],
          "implementsTokenRanges": []
        },
        {
          "kind": "Class",
          "canonicalReference": "@webex/internal-plugin-ediscovery!InvalidEmailAddressError:class",
          "docComment": "/**\n * InvalidEmailAddressError is thrown when an email address has been supplied as a parameter and cannot be found in CI\n */\n",
          "excerptTokens": [
            {
              "kind": "Content",
              "text": "export class InvalidEmailAddressError extends "
            },
            {
              "kind": "Reference",
              "text": "EdiscoveryError",
              "canonicalReference": "@webex/internal-plugin-ediscovery!EdiscoveryError:class"
            },
            {
              "kind": "Content",
              "text": " "
            }
          ],
          "fileUrlPath": "dist/types/ediscovery-error.d.ts",
          "releaseTag": "Public",
          "isAbstract": false,
          "name": "InvalidEmailAddressError",
          "preserveMemberOrder": false,
          "members": [
            {
              "kind": "Method",
              "canonicalReference": "@webex/internal-plugin-ediscovery!InvalidEmailAddressError.getErrorCode:member(1)",
              "docComment": "",
              "excerptTokens": [
                {
                  "kind": "Content",
                  "text": "static getErrorCode(): "
                },
                {
                  "kind": "Content",
                  "text": "number"
                },
                {
                  "kind": "Content",
                  "text": ";"
                }
              ],
              "isStatic": true,
              "returnTypeTokenRange": {
                "startIndex": 1,
                "endIndex": 2
              },
              "releaseTag": "Public",
              "isProtected": false,
              "overloadIndex": 1,
              "parameters": [],
              "isOptional": false,
              "isAbstract": false,
              "name": "getErrorCode"
            }
          ],
          "extendsTokenRange": {
            "startIndex": 1,
            "endIndex": 2
          },
          "implementsTokenRanges": []
        },
        {
          "kind": "Class",
          "canonicalReference": "@webex/internal-plugin-ediscovery!ReportRequest:class",
          "docComment": "/**\n * Creates a report request object with a specific set of search parameters\n *\n * @param name - A label to identify the report\n *\n * @param description - A textual summary of the reports purpose\n *\n * @param emails - A list of user emails relevant to the report\n *\n * @param userIds - A list of UUIDs relevant to the report\n *\n * @param keywords - A list of search terms relevant to the report\n *\n * @param spaceNames - A list of space names relevant to the report\n *\n * @param range - Contains the start time and end time defining the search period\n *\n * @returns {Object} ReportRequest - Contains all search parameters\n */\n",
          "excerptTokens": [
            {
              "kind": "Content",
              "text": "declare class ReportRequest "
            }
          ],
          "fileUrlPath": "dist/types/report-request.d.ts",
          "releaseTag": "Public",
          "isAbstract": false,
          "name": "ReportRequest",
          "preserveMemberOrder": false,
          "members": [
            {
              "kind": "Constructor",
              "canonicalReference": "@webex/internal-plugin-ediscovery!ReportRequest:constructor(1)",
              "docComment": "/**\n * Constructs a new instance of the `ReportRequest` class\n */\n",
              "excerptTokens": [
                {
                  "kind": "Content",
                  "text": "constructor(name?: "
                },
                {
                  "kind": "Content",
                  "text": "string"
                },
                {
                  "kind": "Content",
                  "text": ", description?: "
                },
                {
                  "kind": "Content",
                  "text": "string"
                },
                {
                  "kind": "Content",
                  "text": ", emails?: "
                },
                {
                  "kind": "Content",
                  "text": "any[]"
                },
                {
                  "kind": "Content",
                  "text": ", userIds?: "
                },
                {
                  "kind": "Content",
                  "text": "any[]"
                },
                {
                  "kind": "Content",
                  "text": ", keywords?: "
                },
                {
                  "kind": "Content",
                  "text": "any[]"
                },
                {
                  "kind": "Content",
                  "text": ", encryptionKeyUrl?: "
                },
                {
                  "kind": "Content",
                  "text": "string"
                },
                {
                  "kind": "Content",
                  "text": ", spaceNames?: "
                },
                {
                  "kind": "Content",
                  "text": "any[]"
                },
                {
                  "kind": "Content",
                  "text": ", range?: "
                },
                {
                  "kind": "Content",
                  "text": "{\n        startTime: string;\n        endTime: string;\n    }"
                },
                {
                  "kind": "Content",
                  "text": ");"
                }
              ],
              "releaseTag": "Public",
              "isProtected": false,
              "overloadIndex": 1,
              "parameters": [
                {
                  "parameterName": "name",
                  "parameterTypeTokenRange": {
                    "startIndex": 1,
                    "endIndex": 2
                  },
                  "isOptional": true
                },
                {
                  "parameterName": "description",
                  "parameterTypeTokenRange": {
                    "startIndex": 3,
                    "endIndex": 4
                  },
                  "isOptional": true
                },
                {
                  "parameterName": "emails",
                  "parameterTypeTokenRange": {
                    "startIndex": 5,
                    "endIndex": 6
                  },
                  "isOptional": true
                },
                {
                  "parameterName": "userIds",
                  "parameterTypeTokenRange": {
                    "startIndex": 7,
                    "endIndex": 8
                  },
                  "isOptional": true
                },
                {
                  "parameterName": "keywords",
                  "parameterTypeTokenRange": {
                    "startIndex": 9,
                    "endIndex": 10
                  },
                  "isOptional": true
                },
                {
                  "parameterName": "encryptionKeyUrl",
                  "parameterTypeTokenRange": {
                    "startIndex": 11,
                    "endIndex": 12
                  },
                  "isOptional": true
                },
                {
                  "parameterName": "spaceNames",
                  "parameterTypeTokenRange": {
                    "startIndex": 13,
                    "endIndex": 14
                  },
                  "isOptional": true
                },
                {
                  "parameterName": "range",
                  "parameterTypeTokenRange": {
                    "startIndex": 15,
                    "endIndex": 16
                  },
                  "isOptional": true
                }
              ]
            },
            {
              "kind": "Property",
              "canonicalReference": "@webex/internal-plugin-ediscovery!ReportRequest#description:member",
              "docComment": "",
              "excerptTokens": [
                {
                  "kind": "Content",
                  "text": "description: "
                },
                {
                  "kind": "Content",
                  "text": "string"
                },
                {
                  "kind": "Content",
                  "text": ";"
                }
              ],
              "isReadonly": false,
              "isOptional": false,
              "releaseTag": "Public",
              "name": "description",
              "propertyTypeTokenRange": {
                "startIndex": 1,
                "endIndex": 2
              },
              "isStatic": false,
              "isProtected": false,
              "isAbstract": false
            },
            {
              "kind": "Property",
              "canonicalReference": "@webex/internal-plugin-ediscovery!ReportRequest#emails:member",
              "docComment": "",
              "excerptTokens": [
                {
                  "kind": "Content",
                  "text": "emails: "
                },
                {
                  "kind": "Content",
                  "text": "any[]"
                },
                {
                  "kind": "Content",
                  "text": ";"
                }
              ],
              "isReadonly": false,
              "isOptional": false,
              "releaseTag": "Public",
              "name": "emails",
              "propertyTypeTokenRange": {
                "startIndex": 1,
                "endIndex": 2
              },
              "isStatic": false,
              "isProtected": false,
              "isAbstract": false
            },
            {
              "kind": "Property",
              "canonicalReference": "@webex/internal-plugin-ediscovery!ReportRequest#encryptionKeyUrl:member",
              "docComment": "",
              "excerptTokens": [
                {
                  "kind": "Content",
                  "text": "encryptionKeyUrl: "
                },
                {
                  "kind": "Content",
                  "text": "string"
                },
                {
                  "kind": "Content",
                  "text": ";"
                }
              ],
              "isReadonly": false,
              "isOptional": false,
              "releaseTag": "Public",
              "name": "encryptionKeyUrl",
              "propertyTypeTokenRange": {
                "startIndex": 1,
                "endIndex": 2
              },
              "isStatic": false,
              "isProtected": false,
              "isAbstract": false
            },
            {
              "kind": "Property",
              "canonicalReference": "@webex/internal-plugin-ediscovery!ReportRequest#keywords:member",
              "docComment": "",
              "excerptTokens": [
                {
                  "kind": "Content",
                  "text": "keywords: "
                },
                {
                  "kind": "Content",
                  "text": "any[]"
                },
                {
                  "kind": "Content",
                  "text": ";"
                }
              ],
              "isReadonly": false,
              "isOptional": false,
              "releaseTag": "Public",
              "name": "keywords",
              "propertyTypeTokenRange": {
                "startIndex": 1,
                "endIndex": 2
              },
              "isStatic": false,
              "isProtected": false,
              "isAbstract": false
            },
            {
              "kind": "Property",
              "canonicalReference": "@webex/internal-plugin-ediscovery!ReportRequest#name:member",
              "docComment": "",
              "excerptTokens": [
                {
                  "kind": "Content",
                  "text": "name: "
                },
                {
                  "kind": "Content",
                  "text": "string"
                },
                {
                  "kind": "Content",
                  "text": ";"
                }
              ],
              "isReadonly": false,
              "isOptional": false,
              "releaseTag": "Public",
              "name": "name",
              "propertyTypeTokenRange": {
                "startIndex": 1,
                "endIndex": 2
              },
              "isStatic": false,
              "isProtected": false,
              "isAbstract": false
            },
            {
              "kind": "Property",
              "canonicalReference": "@webex/internal-plugin-ediscovery!ReportRequest#range:member",
              "docComment": "",
              "excerptTokens": [
                {
                  "kind": "Content",
                  "text": "range: "
                },
                {
                  "kind": "Content",
                  "text": "{\n        startTime: string;\n        endTime: string;\n    }"
                },
                {
                  "kind": "Content",
                  "text": ";"
                }
              ],
              "isReadonly": false,
              "isOptional": false,
              "releaseTag": "Public",
              "name": "range",
              "propertyTypeTokenRange": {
                "startIndex": 1,
                "endIndex": 2
              },
              "isStatic": false,
              "isProtected": false,
              "isAbstract": false
            },
            {
              "kind": "Property",
              "canonicalReference": "@webex/internal-plugin-ediscovery!ReportRequest#spaceNames:member",
              "docComment": "",
              "excerptTokens": [
                {
                  "kind": "Content",
                  "text": "spaceNames: "
                },
                {
                  "kind": "Content",
                  "text": "any[]"
                },
                {
                  "kind": "Content",
                  "text": ";"
                }
              ],
              "isReadonly": false,
              "isOptional": false,
              "releaseTag": "Public",
              "name": "spaceNames",
              "propertyTypeTokenRange": {
                "startIndex": 1,
                "endIndex": 2
              },
              "isStatic": false,
              "isProtected": false,
              "isAbstract": false
            },
            {
              "kind": "Property",
              "canonicalReference": "@webex/internal-plugin-ediscovery!ReportRequest#userIds:member",
              "docComment": "",
              "excerptTokens": [
                {
                  "kind": "Content",
                  "text": "userIds: "
                },
                {
                  "kind": "Content",
                  "text": "any[]"
                },
                {
                  "kind": "Content",
                  "text": ";"
                }
              ],
              "isReadonly": false,
              "isOptional": false,
              "releaseTag": "Public",
              "name": "userIds",
              "propertyTypeTokenRange": {
                "startIndex": 1,
                "endIndex": 2
              },
              "isStatic": false,
              "isProtected": false,
              "isAbstract": false
            }
          ],
          "implementsTokenRanges": []
        }
      ]
    }
  ]
}
